AUTHORS.rst
CONTRIBUTING.rst
HISTORY.rst
LICENSE
MANIFEST.in
README.rst
setup.cfg
setup.py
clarify_python_2/__init__.py
clarify_python_2/clarify.py
clarify_python_2/test_op3nvoice.py
clarify_python_2.egg-info/PKG-INFO
clarify_python_2.egg-info/SOURCES.txt
clarify_python_2.egg-info/dependency_links.txt
clarify_python_2.egg-info/not-zip-safe
clarify_python_2.egg-info/top_level.txt