Metadata-Version: 1.1
Name: clarify-python-2
Version: 1.0.1
Summary: The Clarify Python 2 Helper Library wraps the entire Clarify API in Python 2.x function calls.
Home-page: https://github.com/Clarify/clarify_python_2
Author: Paul Murphy
Author-email: murphy@clarify.io
License: MIT
Keywords: clarify_python_2 clarify
Platform: UNKNOWN
Classifier: Development Status :: 5 - Production/Stable
Classifier: Intended Audience :: Developers
Classifier: License :: OSI Approved :: MIT License
Classifier: Natural Language :: English
Classifier: Programming Language :: Python :: 2
Classifier: Programming Language :: Python :: 2.6
Classifier: Programming Language :: Python :: 2.7
